ticketeer_windows/__init__.py
ticketeer_windows-0.1.5.dist-info/METADATA
ticketeer_windows-0.1.5.dist-info/WHEEL
ticketeer_windows-0.1.5.dist-info/top_level.txt
ticketeer_windows-0.1.5.dist-info/RECORD
